Workbook

Sheet 总览
A1: 《疯狂期货》卡牌设计总览
A2: 160 张个人牌 + 20 张公共事件牌｜时间口径：1 回合 = 1 个月，完整游戏 = 连续 8 个月
A4: 核心口径 | B4: 数值 | D4: 个人牌类别 | E4: 不同设计 | F4: 印刷张数 | G4: 占比
A5: 每回合代表时间 | B5: =1&" 个月" -> 1 个月 | D5: 单商品即时信息 | E5: =COUNTIF(个人牌设计!$C$5:$C$71,D5) -> 40 | F5: =SUMIF(个人牌设计!$C$5:$C$71,D5,个人牌设计!$K$5:$K$71) -> 96 | G5: =F5/160 -> 0.6
A6: 完整游戏时间 | B6: =8*1&" 个月" -> 8 个月 | D6: 宏观与联动信息 | E6: =COUNTIF(个人牌设计!$C$5:$C$71,D6) -> 12 | F6: =SUMIF(个人牌设计!$C$5:$C$71,D6,个人牌设计!$K$5:$K$71) -> 24 | G6: =F6/160 -> 0.15
A7: 个人牌不同设计 | B7: =COUNTA(个人牌设计!$A$5:$A$71) -> 67 | D7: 持续信息 | E7: =COUNTIF(个人牌设计!$C$5:$C$71,D7) -> 8 | F7: =SUMIF(个人牌设计!$C$5:$C$71,D7,个人牌设计!$K$5:$K$71) -> 16 | G7: =F7/160 -> 0.1
A8: 个人牌实体张数 | B8: =SUM(个人牌设计!$K$5:$K$71) -> 160 | D8: 功能牌 | E8: =COUNTIF(个人牌设计!$C$5:$C$71,D8) -> 7 | F8: =SUMIF(个人牌设计!$C$5:$C$71,D8,个人牌设计!$K$5:$K$71) -> 24 | G8: =F8/160 -> 0.15
A9: 公共事件牌张数 | B9: =COUNTA(公共事件牌!$A$5:$A$24) -> 20 | D9: 合计 | E9: =SUM(E5:E8) -> 67 | F9: =SUM(F5:F8) -> 160 | G9: =SUM(G5:G8) -> 1
A11: 个人牌强度 | B11: 实体张数 | C11: 占比 | E11: 公共牌强度 | F11: 张数 | G11: 说明
A12: 普通 | B12: =SUMIF(个人牌设计!$D$5:$D$71,A12,个人牌设计!$K$5:$K$71) -> 88 | C12: =B12/160 -> 0.55 | E12: 强烈 | F12: =COUNTIF(公共事件牌!$D$5:$D$24,E12) -> 8 | G12: ±2 格或多商品同步 ±1 格
A13: 强烈 | B13: =SUMIF(个人牌设计!$D$5:$D$71,A13,个人牌设计!$K$5:$K$71) -> 24 | C13: =B13/160 -> 0.15 | E13: 危机 | F13: =COUNTIF(公共事件牌!$D$5:$D$24,E13) -> 4 | G13: 单商品 ±3 格
A14: 危机 | B14: =SUMIF(个人牌设计!$D$5:$D$71,A14,个人牌设计!$K$5:$K$71) -> 8 | C14: =B14/160 -> 0.05 | E14: 趋势 | F14: =COUNTIF(公共事件牌!$D$5:$D$24,E14) -> 4 | G14: 连续 3 个月，每月触发
A15: 趋势 | B15: =SUMIF(个人牌设计!$D$5:$D$71,A15,个人牌设计!$K$5:$K$71) -> 16 | C15: =B15/160 -> 0.1 | E15: 修正 | F15: =COUNTIF(公共事件牌!$D$5:$D$24,E15) -> 3 | G15: 移除一张持续事件
A16: 功能 | B16: =SUMIF(个人牌设计!$D$5:$D$71,A16,个人牌设计!$K$5:$K$71) -> 24 | C16: =B16/160 -> 0.15 | E16: 强修正 | F16: =COUNTIF(公共事件牌!$D$5:$D$24,E16) -> 1 | G16: 移除全部持续事件
A17: 合计 | B17: =SUM(B12:B16) -> 160 | C17: =SUM(C12:C16) -> 1 | E17: 合计 | F17: =SUM(F12:F16) -> 20 | G17: 20 张
A19: 时间规则：第 1—8 回合依次代表第 1—8 个月。个人趋势牌在本月与下个月结算时触发；公共趋势事件在本月及之后两个月结算时触发。若游戏先结束，未触发的剩余月份直接失效。
A22: 强度原则：现货没有单月涨跌上限，所有当月牌效累加；价格表只受阶梯首尾边界限制。卡牌从不直接移动期货价格，期货涨跌停机制保持不变。
A25: 口径提醒：最终版规则书部分章节仍写作 140 张个人信息牌；本工作簿按用户最新确认的 160 张个人牌制作。

Sheet 个人牌设计
A1: 160 张个人牌 - 设计表
A2: 每行代表一种设计；1 回合 = 1 个月。O—X 为公式计算字段，用于核对强度、持续月份与方向平衡。
A4: 设计编号 | B4: 卡名 | C4: 类别 | D4: 强度 | E4: 子类型 | F4: 目标商品 | G4: 使用时点 | H4: 卡面效果 | I4: 持续/月度时点 | J4: 关键词 | K4: 印刷张数 | L4: 方向 | M4: 每月总影响格数 | N4: 作用月数 | O4: 单牌等效总格数 | P4: 牌堆等效总格数 | Q4: 原油每月 | R4: 黄金每月 | S4: 棉花每月 | T4: 铜每月 | U4: 原油牌堆等效 | V4: 黄金牌堆等效 | W4: 棉花牌堆等效 | X4: 铜牌堆等效
A5: PI-OIL-01 | B5: OPEC 超预期减产 | C5: 单商品即时信息 | D5: 普通 | E5: 单次上涨 | F5: 原油 | G5: 出牌阶段 | H5: 原油现货上涨 1 格。 | I5: 本月立即结算；不跨月 | J5: 单次；上涨；普通 | K5: 3 | L5: 上涨 | M5: 1 | N5: 1 | O5: =M5*N5 -> 1 | P5: =K5*O5 -> 3 | Q5: 1 | R5: 0 | S5: 0 | T5: 0 | U5: =K5*N5*Q5 -> 3 | V5: =K5*N5*R5 -> 0 | W5: =K5*N5*S5 -> 0 | X5: =K5*N5*T5 -> 0
A6: PI-OIL-02 | B6: 海湾航道受阻 | C6: 单商品即时信息 | D6: 普通 | E6: 单次上涨 | F6: 原油 | G6: 出牌阶段 | H6: 原油现货上涨 1 格。 | I6: 本月立即结算；不跨月 | J6: 单次；上涨；普通 | K6: 3 | L6: 上涨 | M6: 1 | N6: 1 | O6: =M6*N6 -> 1 | P6: =K6*O6 -> 3 | Q6: 1 | R6: 0 | S6: 0 | T6: 0 | U6: =K6*N6*Q6 -> 3 | V6: =K6*N6*R6 -> 0 | W6: =K6*N6*S6 -> 0 | X6: =K6*N6*T6 -> 0
A7: PI-OIL-03 | B7: 美国原油库存骤降 | C7: 单商品即时信息 | D7: 普通 | E7: 单次上涨 | F7: 原油 | G7: 出牌阶段 | H7: 原油现货上涨 1 格。 | I7: 本月立即结算；不跨月 | J7: 单次；上涨；普通 | K7: 3 | L7: 上涨 | M7: 1 | N7: 1 | O7: =M7*N7 -> 1 | P7: =K7*O7 -> 3 | Q7: 1 | R7: 0 | S7: 0 | T7: 0 | U7: =K7*N7*Q7 -> 3 | V7: =K7*N7*R7 -> 0 | W7: =K7*N7*S7 -> 0 | X7: =K7*N7*T7 -> 0
A8: PI-OIL-04 | B8: 页岩油钻机数大降 | C8: 单商品即时信息 | D8: 强烈 | E8: 单次上涨 | F8: 原油 | G8: 出牌阶段 | H8: 原油现货上涨 2 格。 | I8: 本月立即结算；不跨月 | J8: 单次；上涨；强烈 | K8: 2 | L8: 上涨 | M8: 2 | N8: 1 | O8: =M8*N8 -> 2 | P8: =K8*O8 -> 4 | Q8: 2 | R8: 0 | S8: 0 | T8: 0 | U8: =K8*N8*Q8 -> 4 | V8: =K8*N8*R8 -> 0 | W8: =K8*N8*S8 -> 0 | X8: =K8*N8*T8 -> 0
A9: PI-OIL-05 | B9: 霍尔木兹海峡全面封锁 | C9: 单商品即时信息 | D9: 危机 | E9: 单次上涨 | F9: 原油 | G9: 出牌阶段 | H9: 原油现货上涨 3 格。 | I9: 本月立即结算；不跨月 | J9: 单次；上涨；危机 | K9: 1 | L9: 上涨 | M9: 3 | N9: 1 | O9: =M9*N9 -> 3 | P9: =K9*O9 -> 3 | Q9: 3 | R9: 0 | S9: 0 | T9: 0 | U9: =K9*N9*Q9 -> 3 | V9: =K9*N9*R9 -> 0 | W9: =K9*N9*S9 -> 0 | X9: =K9*N9*T9 -> 0
A10: PI-OIL-06 | B10: OPEC 增产分歧 | C10: 单商品即时信息 | D10: 普通 | E10: 单次下跌 | F10: 原油 | G10: 出牌阶段 | H10: 原油现货下跌 1 格。 | I10: 本月立即结算；不跨月 | J10: 单次；下跌；普通 | K10: 3 | L10: 下跌 | M10: 1 | N10: 1 | O10: =M10*N10 -> 1 | P10: =K10*O10 -> 3 | Q10: -1 | R10: 0 | S10: 0 | T10: 0 | U10: =K10*N10*Q10 -> -3 | V10: =K10*N10*R10 -> 0 | W10: =K10*N10*S10 -> 0 | X10: =K10*N10*T10 -> 0
A11: PI-OIL-07 | B11: 战略储备释放 | C11: 单商品即时信息 | D11: 普通 | E11: 单次下跌 | F11: 原油 | G11: 出牌阶段 | H11: 原油现货下跌 1 格。 | I11: 本月立即结算；不跨月 | J11: 单次；下跌；普通 | K11: 3 | L11: 下跌 | M11: 1 | N11: 1 | O11: =M11*N11 -> 1 | P11: =K11*O11 -> 3 | Q11: -1 | R11: 0 | S11: 0 | T11: 0 | U11: =K11*N11*Q11 -> -3 | V11: =K11*N11*R11 -> 0 | W11: =K11*N11*S11 -> 0 | X11: =K11*N11*T11 -> 0
A12: PI-OIL-08 | B12: 美国库存意外累积 | C12: 单商品即时信息 | D12: 普通 | E12: 单次下跌 | F12: 原油 | G12: 出牌阶段 | H12: 原油现货下跌 1 格。 | I12: 本月立即结算；不跨月 | J12: 单次；下跌；普通 | K12: 3 | L12: 下跌 | M12: 1 | N12: 1 | O12: =M12*N12 -> 1 | P12: =K12*O12 -> 3 | Q12: -1 | R12: 0 | S12: 0 | T12: 0 | U12: =K12*N12*Q12 -> -3 | V12: =K12*N12*R12 -> 0 | W12: =K12*N12*S12 -> 0 | X12: =K12*N12*T12 -> 0
A13: PI-OIL-09 | B13: 全球原油需求骤降 | C13: 单商品即时信息 | D13: 强烈 | E13: 单次下跌 | F13: 原油 | G13: 出牌阶段 | H13: 原油现货下跌 2 格。 | I13: 本月立即结算；不跨月 | J13: 单次；下跌；强烈 | K13: 2 | L13: 下跌 | M13: 2 | N13: 1 | O13: =M13*N13 -> 2 | P13: =K13*O13 -> 4 | Q13: -2 | R13: 0 | S13: 0 | T13: 0 | U13: =K13*N13*Q13 -> -4 | V13: =K13*N13*R13 -> 0 | W13: =K13*N13*S13 -> 0 | X13: =K13*N13*T13 -> 0
A14: PI-OIL-10 | B14: 主要产油国全面价格战 | C14: 单商品即时信息 | D14: 危机 | E14: 单次下跌 | F14: 原油 | G14: 出牌阶段 | H14: 原油现货下跌 3 格。 | I14: 本月立即结算；不跨月 | J14: 单次；下跌；危机 | K14: 1 | L14: 下跌 | M14: 3 | N14: 1 | O14: =M14*N14 -> 3 | P14: =K14*O14 -> 3 | Q14: -3 | R14: 0 | S14: 0 | T14: 0 | U14: =K14*N14*Q14 -> -3 | V14: =K14*N14*R14 -> 0 | W14: =K14*N14*S14 -> 0 | X14: =K14*N14*T14 -> 0
A15: PI-GOLD-01 | B15: 美联储释放降息信号 | C15: 单商品即时信息 | D15: 普通 | E15: 单次上涨 | F15: 黄金 | G15: 出牌阶段 | H15: 黄金现货上涨 1 格。 | I15: 本月立即结算；不跨月 | J15: 单次；上涨；普通 | K15: 3 | L15: 上涨 | M15: 1 | N15: 1 | O15: =M15*N15 -> 1 | P15: =K15*O15 -> 3 | Q15: 0 | R15: 1 | S15: 0 | T15: 0 | U15: =K15*N15*Q15 -> 0 | V15: =K15*N15*R15 -> 3 | W15: =K15*N15*S15 -> 0 | X15: =K15*N15*T15 -> 0
A16: PI-GOLD-02 | B16: 地缘避险升温 | C16: 单商品即时信息 | D16: 普通 | E16: 单次上涨 | F16: 黄金 | G16: 出牌阶段 | H16: 黄金现货上涨 1 格。 | I16: 本月立即结算；不跨月 | J16: 单次；上涨；普通 | K16: 3 | L16: 上涨 | M16: 1 | N16: 1 | O16: =M16*N16 -> 1 | P16: =K16*O16 -> 3 | Q16: 0 | R16: 1 | S16: 0 | T16: 0 | U16: =K16*N16*Q16 -> 0 | V16: =K16*N16*R16 -> 3 | W16: =K16*N16*S16 -> 0 | X16: =K16*N16*T16 -> 0
... A71: PF-07 | B71: 信息置换 | C71: 功能牌 | D71: 功能 | E71: 手牌管理 | F71: 自己 | G71: 出牌阶段 | H71: 抽 2 张个人牌，然后从手中选择 2 张牌弃置。 | I71: 按卡面结算 | J71: 抽牌；弃牌 | K71: 4 | L71: 无直接价格方向 | M71: 0 | N71: 0 | O71: =M71*N71 -> 0 | P71: =K71*O71 -> 0 | Q71: 0 | R71: 0 | S71: 0 | T71: 0 | U71: =K71*N71*Q71 -> 0 | V71: =K71*N71*R71 -> 0 | W71: =K71*N71*S71 -> 0 | X71: =K71*N71*T71 -> 0

Sheet 个人牌印刷清单
A1: 160 张个人牌 - 印刷清单
A2: 每行对应一张实体卡，实体卡编号 P001—P160；时间文案已统一为月份。
A4: 实体卡编号 | B4: 设计编号 | C4: 复本序号 | D4: 卡名 | E4: 类别 | F4: 强度 | G4: 目标 | H4: 卡面效果 | I4: 月度/持续 | J4: 关键词
A5: P001 | B5: PI-OIL-01 | C5: 1 | D5: OPEC 超预期减产 | E5: 单商品即时信息 | F5: 普通 | G5: 原油 | H5: 原油现货上涨 1 格。 | I5: 本月立即结算；不跨月 | J5: 单次；上涨；普通
A6: P002 | B6: PI-OIL-01 | C6: 2 | D6: OPEC 超预期减产 | E6: 单商品即时信息 | F6: 普通 | G6: 原油 | H6: 原油现货上涨 1 格。 | I6: 本月立即结算；不跨月 | J6: 单次；上涨；普通
A7: P003 | B7: PI-OIL-01 | C7: 3 | D7: OPEC 超预期减产 | E7: 单商品即时信息 | F7: 普通 | G7: 原油 | H7: 原油现货上涨 1 格。 | I7: 本月立即结算；不跨月 | J7: 单次；上涨；普通
A8: P004 | B8: PI-OIL-02 | C8: 1 | D8: 海湾航道受阻 | E8: 单商品即时信息 | F8: 普通 | G8: 原油 | H8: 原油现货上涨 1 格。 | I8: 本月立即结算；不跨月 | J8: 单次；上涨；普通
A9: P005 | B9: PI-OIL-02 | C9: 2 | D9: 海湾航道受阻 | E9: 单商品即时信息 | F9: 普通 | G9: 原油 | H9: 原油现货上涨 1 格。 | I9: 本月立即结算；不跨月 | J9: 单次；上涨；普通
A10: P006 | B10: PI-OIL-02 | C10: 3 | D10: 海湾航道受阻 | E10: 单商品即时信息 | F10: 普通 | G10: 原油 | H10: 原油现货上涨 1 格。 | I10: 本月立即结算；不跨月 | J10: 单次；上涨；普通
A11: P007 | B11: PI-OIL-03 | C11: 1 | D11: 美国原油库存骤降 | E11: 单商品即时信息 | F11: 普通 | G11: 原油 | H11: 原油现货上涨 1 格。 | I11: 本月立即结算；不跨月 | J11: 单次；上涨；普通
A12: P008 | B12: PI-OIL-03 | C12: 2 | D12: 美国原油库存骤降 | E12: 单商品即时信息 | F12: 普通 | G12: 原油 | H12: 原油现货上涨 1 格。 | I12: 本月立即结算；不跨月 | J12: 单次；上涨；普通
A13: P009 | B13: PI-OIL-03 | C13: 3 | D13: 美国原油库存骤降 | E13: 单商品即时信息 | F13: 普通 | G13: 原油 | H13: 原油现货上涨 1 格。 | I13: 本月立即结算；不跨月 | J13: 单次；上涨；普通
A14: P010 | B14: PI-OIL-04 | C14: 1 | D14: 页岩油钻机数大降 | E14: 单商品即时信息 | F14: 强烈 | G14: 原油 | H14: 原油现货上涨 2 格。 | I14: 本月立即结算；不跨月 | J14: 单次；上涨；强烈
A15: P011 | B15: PI-OIL-04 | C15: 2 | D15: 页岩油钻机数大降 | E15: 单商品即时信息 | F15: 强烈 | G15: 原油 | H15: 原油现货上涨 2 格。 | I15: 本月立即结算；不跨月 | J15: 单次；上涨；强烈
A16: P012 | B16: PI-OIL-05 | C16: 1 | D16: 霍尔木兹海峡全面封锁 | E16: 单商品即时信息 | F16: 危机 | G16: 原油 | H16: 原油现货上涨 3 格。 | I16: 本月立即结算；不跨月 | J16: 单次；上涨；危机
... A164: P160 | B164: PF-07 | C164: 4 | D164: 信息置换 | E164: 功能牌 | F164: 功能 | G164: 自己 | H164: 抽 2 张个人牌，然后从手中选择 2 张牌弃置。 | I164: 按卡面结算 | J164: 抽牌；弃牌

Sheet 公共事件牌
A1: 20 张公共事件牌
A2: 12 张一次性事件 + 4 张持续事件 + 4 张修正事件｜严重冲击可移动 2—3 格；持续事件按月触发。
A4: 编号 | B4: 事件名称 | C4: 大类 | D4: 强度 | E4: 子类型 | F4: 目标商品 | G4: 卡面效果 | H4: 持续/月度时点 | I4: 关键词 | J4: 原油每月 | K4: 黄金每月 | L4: 棉花每月 | M4: 铜每月 | N4: 每月总影响格数 | O4: 作用月数 | P4: 单牌等效总格数 | Q4: 原油总影响 | R4: 黄金总影响 | S4: 棉花总影响 | T4: 铜总影响
A5: PE-01 | B5: 全球通胀共振 | C5: 一次性事件 | D5: 强烈 | E5: 全商品一次性上涨 | F5: 四种商品 | G5: 原油、黄金、棉花、铜现货各上涨 1 格，然后弃置。 | H5: 本月翻开时立即结算；不跨月 | I5: 单次；强烈 | J5: 1 | K5: 1 | L5: 1 | M5: 1 | N5: 4 | O5: 1 | P5: =N5*O5 -> 4 | Q5: =J5*O5 -> 1 | R5: =K5*O5 -> 1 | S5: =L5*O5 -> 1 | T5: =M5*O5 -> 1
A6: PE-02 | B6: 全球流动性冻结 | C6: 一次性事件 | D6: 强烈 | E6: 全商品一次性下跌 | F6: 四种商品 | G6: 原油、黄金、棉花、铜现货各下跌 1 格，然后弃置。 | H6: 本月翻开时立即结算；不跨月 | I6: 单次；强烈 | J6: -1 | K6: -1 | L6: -1 | M6: -1 | N6: 4 | O6: 1 | P6: =N6*O6 -> 4 | Q6: =J6*O6 -> -1 | R6: =K6*O6 -> -1 | S6: =L6*O6 -> -1 | T6: =M6*O6 -> -1
A7: PE-03 | B7: 海峡封锁升级 | C7: 一次性事件 | D7: 危机 | E7: 单商品一次性上涨 | F7: 原油 | G7: 原油现货上涨 3 格，然后弃置。 | H7: 本月翻开时立即结算；不跨月 | I7: 单次；危机 | J7: 3 | K7: 0 | L7: 0 | M7: 0 | N7: 3 | O7: 1 | P7: =N7*O7 -> 3 | Q7: =J7*O7 -> 3 | R7: =K7*O7 -> 0 | S7: =L7*O7 -> 0 | T7: =M7*O7 -> 0
A8: PE-04 | B8: 国际能源署紧急释放储备 | C8: 一次性事件 | D8: 危机 | E8: 单商品一次性下跌 | F8: 原油 | G8: 原油现货下跌 3 格，然后弃置。 | H8: 本月翻开时立即结算；不跨月 | I8: 单次；危机 | J8: -3 | K8: 0 | L8: 0 | M8: 0 | N8: 3 | O8: 1 | P8: =N8*O8 -> 3 | Q8: =J8*O8 -> -3 | R8: =K8*O8 -> 0 | S8: =L8*O8 -> 0 | T8: =M8*O8 -> 0
A9: PE-05 | B9: 全球央行联合购金 | C9: 一次性事件 | D9: 危机 | E9: 单商品一次性上涨 | F9: 黄金 | G9: 黄金现货上涨 3 格，然后弃置。 | H9: 本月翻开时立即结算；不跨月 | I9: 单次；危机 | J9: 0 | K9: 3 | L9: 0 | M9: 0 | N9: 3 | O9: 1 | P9: =N9*O9 -> 3 | Q9: =J9*O9 -> 0 | R9: =K9*O9 -> 3 | S9: =L9*O9 -> 0 | T9: =M9*O9 -> 0
A10: PE-06 | B10: 美联储极端鹰派冲击 | C10: 一次性事件 | D10: 危机 | E10: 单商品一次性下跌 | F10: 黄金 | G10: 黄金现货下跌 3 格，然后弃置。 | H10: 本月翻开时立即结算；不跨月 | I10: 单次；危机 | J10: 0 | K10: -3 | L10: 0 | M10: 0 | N10: 3 | O10: 1 | P10: =N10*O10 -> 3 | Q10: =J10*O10 -> 0 | R10: =K10*O10 -> -3 | S10: =L10*O10 -> 0 | T10: =M10*O10 -> 0
A11: PE-07 | B11: 主产区百年干旱 | C11: 一次性事件 | D11: 强烈 | E11: 单商品一次性上涨 | F11: 棉花 | G11: 棉花现货上涨 2 格，然后弃置。 | H11: 本月翻开时立即结算；不跨月 | I11: 单次；强烈 | J11: 0 | K11: 0 | L11: 2 | M11: 0 | N11: 2 | O11: 1 | P11: =N11*O11 -> 2 | Q11: =J11*O11 -> 0 | R11: =K11*O11 -> 0 | S11: =L11*O11 -> 2 | T11: =M11*O11 -> 0
A12: PE-08 | B12: 全球棉花超级丰收 | C12: 一次性事件 | D12: 强烈 | E12: 单商品一次性下跌 | F12: 棉花 | G12: 棉花现货下跌 2 格，然后弃置。 | H12: 本月翻开时立即结算；不跨月 | I12: 单次；强烈 | J12: 0 | K12: 0 | L12: -2 | M12: 0 | N12: 2 | O12: 1 | P12: =N12*O12 -> 2 | Q12: =J12*O12 -> 0 | R12: =K12*O12 -> 0 | S12: =L12*O12 -> -2 | T12: =M12*O12 -> 0
A13: PE-09 | B13: 全球电网投资浪潮 | C13: 一次性事件 | D13: 强烈 | E13: 单商品一次性上涨 | F13: 铜 | G13: 铜现货上涨 2 格，然后弃置。 | H13: 本月翻开时立即结算；不跨月 | I13: 单次；强烈 | J13: 0 | K13: 0 | L13: 0 | M13: 2 | N13: 2 | O13: 1 | P13: =N13*O13 -> 2 | Q13: =J13*O13 -> 0 | R13: =K13*O13 -> 0 | S13: =L13*O13 -> 0 | T13: =M13*O13 -> 2
A14: PE-10 | B14: 全球地产去杠杆冲击 | C14: 一次性事件 | D14: 强烈 | E14: 单商品一次性下跌 | F14: 铜 | G14: 铜现货下跌 2 格，然后弃置。 | H14: 本月翻开时立即结算；不跨月 | I14: 单次；强烈 | J14: 0 | K14: 0 | L14: 0 | M14: -2 | N14: 2 | O14: 1 | P14: =N14*O14 -> 2 | Q14: =J14*O14 -> 0 | R14: =K14*O14 -> 0 | S14: =L14*O14 -> 0 | T14: =M14*O14 -> -2
A15: PE-11 | B15: 全球供应链中断 | C15: 一次性事件 | D15: 强烈 | E15: 多商品一次性上涨 | F15: 棉花、铜 | G15: 棉花与铜现货各上涨 1 格，然后弃置。 | H15: 本月翻开时立即结算；不跨月 | I15: 单次；强烈 | J15: 0 | K15: 0 | L15: 1 | M15: 1 | N15: 2 | O15: 1 | P15: =N15*O15 -> 2 | Q15: =J15*O15 -> 0 | R15: =K15*O15 -> 0 | S15: =L15*O15 -> 1 | T15: =M15*O15 -> 1
A16: PE-12 | B16: 全球供应链全面修复 | C16: 一次性事件 | D16: 强烈 | E16: 多商品一次性下跌 | F16: 棉花、铜 | G16: 棉花与铜现货各下跌 1 格，然后弃置。 | H16: 本月翻开时立即结算；不跨月 | I16: 单次；强烈 | J16: 0 | K16: 0 | L16: -1 | M16: -1 | N16: 2 | O16: 1 | P16: =N16*O16 -> 2 | Q16: =J16*O16 -> 0 | R16: =K16*O16 -> 0 | S16: =L16*O16 -> -1 | T16: =M16*O16 -> -1
... A24: PE-20 | B24: 多国政策协调声明 | C24: 修正事件 | D24: 强修正 | E24: 移除全部持续事件 | F24: 全部持续公共事件 | G24: 移除场上全部持续公共事件；不逆转以前月份已经发生的价格移动。 | H24: 本月翻开时立即结算 | I24: 移除；强修正 | J24: 0 | K24: 0 | L24: 0 | M24: 0 | N24: 0 | O24: 0 | P24: =N24*O24 -> 0 | Q24: =J24*O24 -> 0 | R24: =K24*O24 -> 0 | S24: =L24*O24 -> 0 | T24: =M24*O24 -> 0

Sheet 平衡校验
A1: 数量、强度与方向平衡校验
A2: 所有关键指标使用工作表公式计算；等效格数 = 每月影响 × 作用月数 × 印刷张数。
A4: 数量检查 | B4: 实际值 | C4: 目标值 | D4: 状态
A5: 个人牌不同设计 | B5: =COUNTA(个人牌设计!$A$5:$A$71) -> 67 | C5: 67 | D5: =IF(B5=C5,"通过","检查") -> 通过
A6: 个人牌实体张数 | B6: =SUM(个人牌设计!$K$5:$K$71) -> 160 | C6: 160 | D6: =IF(B6=C6,"通过","检查") -> 通过
A7: 个人牌印刷清单行数 | B7: =COUNTA(个人牌印刷清单!$A$5:$A$164) -> 160 | C7: 160 | D7: =IF(B7=C7,"通过","检查") -> 通过
A8: 公共事件牌张数 | B8: =COUNTA(公共事件牌!$A$5:$A$24) -> 20 | C8: 20 | D8: =IF(B8=C8,"通过","检查") -> 通过
A9: 每回合对应月份 | B9: =1 -> 1 | C9: 1 | D9: =IF(B9=C9,"通过","检查") -> 通过
A10: 完整游戏月份 | B10: =8*B9 -> 8 | C10: 8 | D10: =IF(B10=C10,"通过","检查") -> 通过
A12: 个人牌类别 | B12: 实体张数 | C12: 目标值 | D12: 状态
A13: 单商品即时信息 | B13: =SUMIF(个人牌设计!$C$5:$C$71,A13,个人牌设计!$K$5:$K$71) -> 96 | C13: 96 | D13: =IF(B13=C13,"通过","检查") -> 通过
A14: 宏观与联动信息 | B14: =SUMIF(个人牌设计!$C$5:$C$71,A14,个人牌设计!$K$5:$K$71) -> 24 | C14: 24 | D14: =IF(B14=C14,"通过","检查") -> 通过
A15: 持续信息 | B15: =SUMIF(个人牌设计!$C$5:$C$71,A15,个人牌设计!$K$5:$K$71) -> 16 | C15: 16 | D15: =IF(B15=C15,"通过","检查") -> 通过
A16: 功能牌 | B16: =SUMIF(个人牌设计!$C$5:$C$71,A16,个人牌设计!$K$5:$K$71) -> 24 | C16: 24 | D16: =IF(B16=C16,"通过","检查") -> 通过
A17: 合计 | B17: =SUM(B13:B16) -> 160 | C17: 160 | D17: =IF(B17=C17,"通过","检查") -> 通过
A19: 个人牌强度 | B19: 实体张数 | C19: 目标值 | D19: 状态
A20: 普通 | B20: =SUMIF(个人牌设计!$D$5:$D$71,A20,个人牌设计!$K$5:$K$71) -> 88 | C20: 88 | D20: =IF(B20=C20,"通过","检查") -> 通过
A21: 强烈 | B21: =SUMIF(个人牌设计!$D$5:$D$71,A21,个人牌设计!$K$5:$K$71) -> 24 | C21: 24 | D21: =IF(B21=C21,"通过","检查") -> 通过
A22: 危机 | B22: =SUMIF(个人牌设计!$D$5:$D$71,A22,个人牌设计!$K$5:$K$71) -> 8 | C22: 8 | D22: =IF(B22=C22,"通过","检查") -> 通过
A23: 趋势 | B23: =SUMIF(个人牌设计!$D$5:$D$71,A23,个人牌设计!$K$5:$K$71) -> 16 | C23: 16 | D23: =IF(B23=C23,"通过","检查") -> 通过
A24: 功能 | B24: =SUMIF(个人牌设计!$D$5:$D$71,A24,个人牌设计!$K$5:$K$71) -> 24 | C24: 24 | D24: =IF(B24=C24,"通过","检查") -> 通过
A25: 合计 | B25: =SUM(B20:B24) -> 160 | C25: 160 | D25: =IF(B25=C25,"通过","检查") -> 通过
A27: 单商品个人牌 | B27: 上涨张数 | C27: 下跌张数 | D27: 上涨等效格数 | E27: 下跌等效格数 | F27: 状态
A28: 原油 | B28: =SUM(个人牌设计!$K$5:$K$9) -> 12 | C28: =SUM(个人牌设计!$K$10:$K$14) -> 12 | D28: =SUM(个人牌设计!$U$5:$U$9) -> 16 | E28: =-SUM(个人牌设计!$U$10:$U$14) -> 16 | F28: =IF(AND(B28=C28,D28=E28),"通过","检查") -> 通过
A29: 黄金 | B29: =SUM(个人牌设计!$K$15:$K$19) -> 12 | C29: =SUM(个人牌设计!$K$20:$K$24) -> 12 | D29: =SUM(个人牌设计!$V$15:$V$19) -> 16 | E29: =-SUM(个人牌设计!$V$20:$V$24) -> 16 | F29: =IF(AND(B29=C29,D29=E29),"通过","检查") -> 通过
A30: 棉花 | B30: =SUM(个人牌设计!$K$25:$K$29) -> 12 | C30: =SUM(个人牌设计!$K$30:$K$34) -> 12 | D30: =SUM(个人牌设计!$W$25:$W$29) -> 16 | E30: =-SUM(个人牌设计!$W$30:$W$34) -> 16 | F30: =IF(AND(B30=C30,D30=E30),"通过","检查") -> 通过
A31: 铜 | B31: =SUM(个人牌设计!$K$35:$K$39) -> 12 | C31: =SUM(个人牌设计!$K$40:$K$44) -> 12 | D31: =SUM(个人牌设计!$X$35:$X$39) -> 16 | E31: =-SUM(个人牌设计!$X$40:$X$44) -> 16 | F31: =IF(AND(B31=C31,D31=E31),"通过","检查") -> 通过
A33: 按完整持续期计算 | B33: 个人趋势上涨 | C33: 个人趋势下跌 | D33: 公共趋势上涨 | E33: 公共趋势下跌 | F33: 状态
A34: 原油 | B34: =个人牌设计!$U$57 -> 4 | C34: =-个人牌设计!$U$58 -> 4 | D34: =公共事件牌!$Q$19 -> 3 | E34: =-公共事件牌!$Q$20 -> 3 | F34: =IF(AND(B34=C34,D34=E34),"通过","检查") -> 通过
A35: 黄金 | B35: =个人牌设计!$V$59 -> 4 | C35: =-个人牌设计!$V$60 -> 4 | D35: =公共事件牌!$R$17 -> 3 | E35: =-公共事件牌!$R$18 -> 3 | F35: =IF(AND(B35=C35,D35=E35),"通过","检查") -> 通过
A36: 棉花 | B36: =个人牌设计!$W$61 -> 4 | C36: =-个人牌设计!$W$62 -> 4 | D36: =公共事件牌!$S$19 -> 3 | E36: =-公共事件牌!$S$20 -> 3 | F36: =IF(AND(B36=C36,D36=E36),"通过","检查") -> 通过
A37: 铜 | B37: =个人牌设计!$X$63 -> 4 | C37: =-个人牌设计!$X$64 -> 4 | D37: =公共事件牌!$T$17 -> 3 | E37: =-公共事件牌!$T$18 -> 3 | F37: =IF(AND(B37=C37,D37=E37),"通过","检查") -> 通过
A39: 公共一次性事件 | B39: 累计上涨格数 | C39: 累计下跌格数 | D39: 净偏置 | E39: 目标 | F39: 状态
A40: 原油 | B40: =公共事件牌!$Q$5+公共事件牌!$Q$7 -> 4 | C40: =-(公共事件牌!$Q$6+公共事件牌!$Q$8) -> 4 | D40: =B40-C40 -> 0 | E40: =0 -> 0 | F40: =IF(D40=E40,"通过","检查") -> 通过
A41: 黄金 | B41: =公共事件牌!$R$5+公共事件牌!$R$9 -> 4 | C41: =-(公共事件牌!$R$6+公共事件牌!$R$10) -> 4 | D41: =B41-C41 -> 0 | E41: =0 -> 0 | F41: =IF(D41=E41,"通过","检查") -> 通过
A42: 棉花 | B42: =公共事件牌!$S$5+公共事件牌!$S$11+公共事件牌!$S$15 -> 4 | C42: =-(公共事件牌!$S$6+公共事件牌!$S$12+公共事件牌!$S$16) -> 4 | D42: =B42-C42 -> 0 | E42: =0 -> 0 | F42: =IF(D42=E42,"通过","检查") -> 通过
A43: 铜 | B43: =公共事件牌!$T$5+公共事件牌!$T$13+公共事件牌!$T$15 -> 4 | C43: =-(公共事件牌!$T$6+公共事件牌!$T$14+公共事件牌!$T$16) -> 4 | D43: =B43-C43 -> 0 | E43: =0 -> 0 | F43: =IF(D43=E43,"通过","检查") -> 通过
A45: 解释：普通个人牌每张 ±1 格；强烈牌为 ±2 格或双商品各 ±1 格；危机牌为 ±3 格。个人趋势持续 2 个月，公共趋势持续 3 个月。现货无单月涨跌上限，因此同月翻开的多张事件和玩家打出的多张牌均累加。
